EleganceReport/EleganceReport.py
EleganceReport/__init__.py
EleganceReport/img/__init__.py
EleganceReport/sample/__init__.py
EleganceReport/sample/sample.py
EleganceReport/template/__init__.py
EleganceReport/template/template
EleganceReport/template/template.html
EleganceReport/template/theme.json
EleganceReport/template/theme_candy.json
EleganceReport/template/theme_cyan.json
EleganceReport/template/theme_default.json
EleganceReport/template/theme_memories.json
EleganceReport/tests/__init__.py
EleganceReport/tests/test_make_report.py
EleganceReport-0.2.5.dist-info/LICENSE
EleganceReport-0.2.5.dist-info/METADATA
EleganceReport-0.2.5.dist-info/WHEEL
EleganceReport-0.2.5.dist-info/top_level.txt
EleganceReport-0.2.5.dist-info/RECORD
