Metadata-Version: 2.1
Name: EleganceReport
Version: 0.2.5
Summary: 迄今为止最好看的测试报告
Home-page: https://github.com/pypa/sampleproject
Author: 曾润平
Author-email: 1450644462@qq.com
License: UNKNOWN
Platform: UNKNOWN
Classifier: Programming Language :: Python :: 3
Classifier: License :: OSI Approved :: MIT License
Classifier: Operating System :: OS Independent
Requires-Python: >=3.6
